pythonray/Payload.py
pythonray/__init__.py
pythonray/hello.py
pythonray/ray.py
pythonray-0.1.6.dist-info/LICENSE.txt
pythonray-0.1.6.dist-info/METADATA
pythonray-0.1.6.dist-info/WHEEL
pythonray-0.1.6.dist-info/top_level.txt
pythonray-0.1.6.dist-info/RECORD
