Metadata-Version: 2.1
Name: pythonray
Version: 0.1.6
Summary: A package to send messages to Spatie's Ray from Python
Author: Harry Lipnick
Author-email: harry.lipnick@gmail.com
Keywords: python,ray,spatie
License-File: LICENSE.txt
Requires-Dist: requests
